eaglesong/__init__.py
eaglesong/core/__init__.py
eaglesong/core/automaton.py
eaglesong/core/interpreter.py
eaglesong/core/primitives.py
eaglesong/core/translator.py
eaglesong/core/testing/__init__.py
eaglesong/core/testing/helping_types.py
eaglesong/core/testing/scenario.py
eaglesong/core/testing/testing_interpreter.py
eaglesong/drivers/__init__.py
eaglesong/drivers/telegram/__init__.py
eaglesong/drivers/telegram/menu.py
eaglesong/drivers/telegram/telegram_driver.py
eaglesong/drivers/telegram/telegram_interpreters.py
eaglesong/drivers/telegram/telegram_service.py
eaglesong/drivers/telegram/telegram_simplifier.py
eaglesong/drivers/telegram/telegram_translator.py
eaglesong/drivers/telegram/primitives/__init__.py
eaglesong/drivers/telegram/primitives/bot.py
eaglesong/drivers/telegram/primitives/telegram.py
eaglesong/drivers/telegram/testing/__init__.py
eaglesong/drivers/telegram/testing/feedback.py
eaglesong/drivers/telegram/testing/scenario.py
eaglesong/drivers/telegram/testing/validators.py
kaia_eaglesong-4.0.9.dist-info/METADATA
kaia_eaglesong-4.0.9.dist-info/WHEEL
kaia_eaglesong-4.0.9.dist-info/top_level.txt
kaia_eaglesong-4.0.9.dist-info/RECORD
